lucyparser/__init__.py
lucyparser/cursor.py
lucyparser/exceptions.py
lucyparser/parsing.py
lucyparser/tree.py
lucyparser-0.2.2.dist-info/WHEEL
lucyparser-0.2.2.dist-info/METADATA
lucyparser-0.2.2.dist-info/RECORD
