Metadata-Version: 2.1
Name: lucyparser
Version: 0.2.2
Summary: Lucene-like syntax parser
Author: Timur
Author-email: timur.makarchuk@gmail.com
Requires-Python: >=3.7,<4.0
Classifier: Programming Language :: Python :: 3
Classifier: Programming Language :: Python :: 3.7
Classifier: Programming Language :: Python :: 3.8
